sphinxnotes/snippet/__init__.py
sphinxnotes/snippet/cache.py
sphinxnotes/snippet/cli.py
sphinxnotes/snippet/ext.py
sphinxnotes/snippet/keyword.py
sphinxnotes/snippet/meta.py
sphinxnotes/snippet/picker.py
sphinxnotes/snippet/py.typed
sphinxnotes/snippet/snippets.py
sphinxnotes/snippet/table.py
sphinxnotes/snippet/config/__init__.py
sphinxnotes/snippet/config/default.py
sphinxnotes/snippet/integration/__init__.py
sphinxnotes/snippet/integration/binding.nvim
sphinxnotes/snippet/integration/binding.sh
sphinxnotes/snippet/integration/binding.vim
sphinxnotes/snippet/integration/binding.zsh
sphinxnotes/snippet/integration/plugin.sh
sphinxnotes/snippet/integration/plugin.vim
sphinxnotes/snippet/utils/__init__.py
sphinxnotes/snippet/utils/ellipsis.py
sphinxnotes/snippet/utils/pdict.py
sphinxnotes/snippet/utils/titlepath.py
sphinxnotes_snippet-1.3.dist-info/licenses/LICENSE
sphinxnotes_snippet-1.3.dist-info/METADATA
sphinxnotes_snippet-1.3.dist-info/WHEEL
sphinxnotes_snippet-1.3.dist-info/entry_points.txt
sphinxnotes_snippet-1.3.dist-info/top_level.txt
sphinxnotes_snippet-1.3.dist-info/RECORD
